molecule_alicloud/__init__.py
molecule_alicloud/driver.py
molecule_alicloud/cookiecutter/cookiecutter.json
molecule_alicloud/cookiecutter/{{cookiecutter.molecule_directory}}/{{cookiecutter.scenario_name}}/INSTALL.rst
molecule_alicloud/cookiecutter/{{cookiecutter.molecule_directory}}/{{cookiecutter.scenario_name}}/converge.yml
molecule_alicloud/cookiecutter/{{cookiecutter.molecule_directory}}/{{cookiecutter.scenario_name}}/create.yml
molecule_alicloud/cookiecutter/{{cookiecutter.molecule_directory}}/{{cookiecutter.scenario_name}}/destroy.yml
molecule_alicloud/cookiecutter/{{cookiecutter.molecule_directory}}/{{cookiecutter.scenario_name}}/prepare.yml
molecule_alicloud/test/__init__.py
molecule_alicloud/test/test_driver.py
molecule_alicloud/test/functional/__init__.py
molecule_alicloud/test/functional/conftest.py
molecule_alicloud/test/functional/test_ecs.py
molecule_ecs/__init__.py
molecule_ecs/driver.py
molecule_ecs/cookiecutter/cookiecutter.json
molecule_ecs/cookiecutter/{{cookiecutter.molecule_directory}}/{{cookiecutter.scenario_name}}/INSTALL.rst
molecule_ecs/cookiecutter/{{cookiecutter.molecule_directory}}/{{cookiecutter.scenario_name}}/converge.yml
molecule_ecs/cookiecutter/{{cookiecutter.molecule_directory}}/{{cookiecutter.scenario_name}}/create.yml
molecule_ecs/cookiecutter/{{cookiecutter.molecule_directory}}/{{cookiecutter.scenario_name}}/destroy.yml
molecule_ecs/cookiecutter/{{cookiecutter.molecule_directory}}/{{cookiecutter.scenario_name}}/prepare.yml
molecule_ecs/test/__init__.py
molecule_ecs/test/test_driver.py
molecule_ecs/test/functional/__init__.py
molecule_ecs/test/functional/conftest.py
molecule_ecs/test/functional/test_ecs.py
molecule_alicloud-0.1.dev0.dist-info/LICENSE
molecule_alicloud-0.1.dev0.dist-info/METADATA
molecule_alicloud-0.1.dev0.dist-info/WHEEL
molecule_alicloud-0.1.dev0.dist-info/entry_points.txt
molecule_alicloud-0.1.dev0.dist-info/top_level.txt
molecule_alicloud-0.1.dev0.dist-info/RECORD
