Metadata-Version: 2.1
Name: molecule-alicloud
Version: 0.1.dev0
Summary: AliCloud ECS Molecule Plugin :: run molecule tests using AliCloud ECS (Aliyun ECS)
Home-page: https://github.com/ansible-community/molecule-alicloud
Author: Yang Liu
Author-email: liuyangc3@gmail.com
Maintainer: Yang Liu
Maintainer-email: liuyangc3@gmail.com
License: MIT
Project-URL: Bug Tracker, https://github.com/ansible-community/molecule-alicloud/issues
Project-URL: Release Management, https://github.com/ansible-community/molecule-alicloud/releases
Project-URL: CI: Zuul, https://dashboard.zuul.ansible.com/t/ansible/builds?project=ansible-community/molecule-alicloud
Project-URL: Source Code, https://github.com/ansible-community/molecule-alicloud
Keywords: ansible,roles,testing,molecule,plugin,ecs,alicloud,aliyun,alibaba
Platform: UNKNOWN
Classifier: Development Status :: 3 - Alpha
Classifier: Environment :: Console
Classifier: Framework :: Pytest
Classifier: Intended Audience :: Developers
Classifier: Intended Audience :: Information Technology
Classifier: Intended Audience :: System Administrators
Classifier: License :: OSI Approved :: MIT License
Classifier: Natural Language :: English
Classifier: Operating System :: OS Independent
Classifier: Programming Language :: Python :: 3
Classifier: Programming Language :: Python :: 3.6
Classifier: Programming Language :: Python :: 3.7
Classifier: Topic :: System :: Systems Administration
Classifier: Topic :: Utilities
Requires-Python: >=3.6
Requires-Dist: ansible (>=2.9.5)
Requires-Dist: molecule (>=3.0.2)
Requires-Dist: pyyaml (<6,>=5.1)
Requires-Dist: ansible-alicloud
Requires-Dist: ansible-alicloud-module-utils
Provides-Extra: test
Requires-Dist: ansi2html ; extra == 'test'
Requires-Dist: flake8 (<4,>=3.6.0) ; extra == 'test'
Requires-Dist: mock (<4,>=3.0.5) ; extra == 'test'
Requires-Dist: pytest (<5,>=4.6.3) ; extra == 'test'
Requires-Dist: pytest-cov (<3,>=2.7.1) ; extra == 'test'
Requires-Dist: pytest-helpers-namespace (<2020,>=2019.1.8) ; extra == 'test'
Requires-Dist: pytest-html ; extra == 'test'
Requires-Dist: pytest-mock (<2,>=1.10.4) ; extra == 'test'
Requires-Dist: pytest-plus ; extra == 'test'
Requires-Dist: pytest-verbose-parametrize (<2,>=1.7.0) ; extra == 'test'
Requires-Dist: pytest-xdist (<2,>=1.29.0) ; extra == 'test'
Requires-Dist: pytest-dependency ; extra == 'test'
Requires-Dist: shade (<2,>=1.31.0) ; extra == 'test'
